{
  "uuid": "fae2e306-8777-4f61-9ec8-a34f9a13c7bf",
  "lastMigration": 27,
  "name": "Reports>Employees",
  "endpointPrefix": "reports/employees",
  "latency": 0,
  "port": 4360,
  "hostname": "",
  "folders": [
    {
      "uuid": "f096c391-569a-4824-8269-42c7f13e8039",
      "name": "Activity",
      "collapsed": false,
      "children": [
        {
          "type": "route",
          "uuid": "30ff5d5e-8122-4315-9323-70e228886fc5"
        },
        {
          "type": "route",
          "uuid": "8cab63d3-87ce-4613-a746-0404d3149b49"
        }
      ]
    },
    {
      "uuid": "d6238eae-e512-4336-bb08-7867f5f57203",
      "name": "Salary",
      "collapsed": false,
      "children": [
        {
          "type": "route",
          "uuid": "8d576b3c-a978-4102-b88a-f9c2d5388a4e"
        },
        {
          "type": "route",
          "uuid": "4cb59ef7-19e6-4a69-8ea0-12a93efbea04"
        }
      ]
    }
  ],
  "routes": [
    {
      "uuid": "30ff5d5e-8122-4315-9323-70e228886fc5",
      "type": "http",
      "documentation": "",
      "method": "get",
      "endpoint": "activity",
      "responses": [
        {
          "uuid": "c55da6dc-f123-4904-92c0-adf0b5874652",
          "body": "{}",
          "latency": 0,
          "statusCode": 200,
          "label": "page-open response",
          "headers": [
            {
              "key": "Content-Type",
              "value": "application/json"
            }
          ],
          "bodyType": "FILE",
          "filePath": "./activity/page_open.json",
          "databucketID": "",
          "sendFileAsBody": true,
          "rules": [
            {
              "target": "query",
              "modifier": "act",
              "value": "page",
              "invert": false,
              "operator": "equals"
            },
            {
              "target": "query",
              "modifier": "type",
              "value": "open",
              "invert": false,
              "operator": "equals"
            }
          ],
          "rulesOperator": "AND",
          "disableTemplating": false,
          "fallbackTo404": false,
          "default": true
        },
        {
          "uuid": "55627283-c48d-4276-b457-8e00fc77c468",
          "body": "{}",
          "latency": 0,
          "statusCode": 200,
          "label": "absents-tab response",
          "headers": [
            {
              "key": "Content-Type",
              "value": "application/json"
            }
          ],
          "bodyType": "FILE",
          "filePath": "./activity/absents_tab.json",
          "databucketID": "",
          "sendFileAsBody": true,
          "rules": [
            {
              "target": "query",
              "modifier": "act",
              "value": "absents",
              "invert": false,
              "operator": "equals"
            },
            {
              "target": "query",
              "modifier": "type",
              "value": "tab",
              "invert": false,
              "operator": "equals"
            }
          ],
          "rulesOperator": "AND",
          "disableTemplating": false,
          "fallbackTo404": false,
          "default": false
        },
        {
          "uuid": "36fce559-87e8-4243-9348-d0c478125a36",
          "body": "{}",
          "latency": 0,
          "statusCode": 200,
          "label": "absents-report response",
          "headers": [
            {
              "key": "Content-Type",
              "value": "application/json"
            }
          ],
          "bodyType": "FILE",
          "filePath": "./activity/absents_report.json",
          "databucketID": "",
          "sendFileAsBody": true,
          "rules": [
            {
              "target": "query",
              "modifier": "act",
              "value": "absents",
              "invert": false,
              "operator": "equals"
            },
            {
              "target": "query",
              "modifier": "type",
              "value": "report",
              "invert": false,
              "operator": "equals"
            }
          ],
          "rulesOperator": "AND",
          "disableTemplating": false,
          "fallbackTo404": false,
          "default": false
        },
        {
          "uuid": "700cb940-83d1-4418-9106-cf858ba6ac3e",
          "body": "{}",
          "latency": 0,
          "statusCode": 200,
          "label": "overtime-tab response",
          "headers": [
            {
              "key": "Content-Type",
              "value": "application/json"
            }
          ],
          "bodyType": "FILE",
          "filePath": "./activity/overtime_tab.json",
          "databucketID": "",
          "sendFileAsBody": true,
          "rules": [
            {
              "target": "query",
              "modifier": "act",
              "value": "overtime",
              "invert": false,
              "operator": "equals"
            },
            {
              "target": "query",
              "modifier": "type",
              "value": "tab",
              "invert": false,
              "operator": "equals"
            }
          ],
          "rulesOperator": "AND",
          "disableTemplating": false,
          "fallbackTo404": false,
          "default": false
        },
        {
          "uuid": "ec80681e-c6a7-46b5-9df1-c75979bc0399",
          "body": "{}",
          "latency": 0,
          "statusCode": 200,
          "label": "overtime-report response",
          "headers": [
            {
              "key": "Content-Type",
              "value": "application/json"
            }
          ],
          "bodyType": "FILE",
          "filePath": "./activity/overtime_report.json",
          "databucketID": "",
          "sendFileAsBody": true,
          "rules": [
            {
              "target": "query",
              "modifier": "act",
              "value": "overtime",
              "invert": false,
              "operator": "equals"
            },
            {
              "target": "query",
              "modifier": "type",
              "value": "report",
              "invert": false,
              "operator": "equals"
            }
          ],
          "rulesOperator": "AND",
          "disableTemplating": false,
          "fallbackTo404": false,
          "default": false
        },
        {
          "uuid": "9bf14c62-f685-4744-95fe-424b3595c108",
          "body": "{}",
          "latency": 0,
          "statusCode": 200,
          "label": "expenses-tab response",
          "headers": [
            {
              "key": "Content-Type",
              "value": "application/json"
            }
          ],
          "bodyType": "FILE",
          "filePath": "./activity/expenses_tab.json",
          "databucketID": "",
          "sendFileAsBody": true,
          "rules": [
            {
              "target": "query",
              "modifier": "act",
              "value": "expenses",
              "invert": false,
              "operator": "equals"
            },
            {
              "target": "query",
              "modifier": "type",
              "value": "tab",
              "invert": false,
              "operator": "equals"
            }
          ],
          "rulesOperator": "AND",
          "disableTemplating": false,
          "fallbackTo404": false,
          "default": false
        },
        {
          "uuid": "fc4f393b-6b9c-4f8c-8153-2e03629da997",
          "body": "{}",
          "latency": 0,
          "statusCode": 200,
          "label": "expenses-report response",
          "headers": [
            {
              "key": "Content-Type",
              "value": "application/json"
            }
          ],
          "bodyType": "FILE",
          "filePath": "./activity/expenses_report.json",
          "databucketID": "",
          "sendFileAsBody": true,
          "rules": [
            {
              "target": "query",
              "modifier": "act",
              "value": "expenses",
              "invert": false,
              "operator": "equals"
            },
            {
              "target": "query",
              "modifier": "type",
              "value": "report",
              "invert": false,
              "operator": "equals"
            }
          ],
          "rulesOperator": "AND",
          "disableTemplating": false,
          "fallbackTo404": false,
          "default": false
        },
        {
          "uuid": "9558559a-c8dc-4d65-b3f1-55833fa7f89a",
          "body": "{}",
          "latency": 0,
          "statusCode": 200,
          "label": "shortage-tab response",
          "headers": [
            {
              "key": "Content-Type",
              "value": "application/json"
            }
          ],
          "bodyType": "FILE",
          "filePath": "./activity/shortage_tab.json",
          "databucketID": "",
          "sendFileAsBody": true,
          "rules": [
            {
              "target": "query",
              "modifier": "act",
              "value": "shortage",
              "invert": false,
              "operator": "equals"
            },
            {
              "target": "query",
              "modifier": "type",
              "value": "tab",
              "invert": false,
              "operator": "equals"
            }
          ],
          "rulesOperator": "AND",
          "disableTemplating": false,
          "fallbackTo404": false,
          "default": false
        },
        {
          "uuid": "4df891f5-c7e4-46d4-b661-d4d2652e3417",
          "body": "{}",
          "latency": 0,
          "statusCode": 200,
          "label": "shortage-report response",
          "headers": [
            {
              "key": "Content-Type",
              "value": "application/json"
            }
          ],
          "bodyType": "FILE",
          "filePath": "./activity/shortage_report.json",
          "databucketID": "",
          "sendFileAsBody": true,
          "rules": [
            {
              "target": "query",
              "modifier": "act",
              "value": "shortage",
              "invert": false,
              "operator": "equals"
            },
            {
              "target": "query",
              "modifier": "type",
              "value": "report",
              "invert": false,
              "operator": "equals"
            }
          ],
          "rulesOperator": "AND",
          "disableTemplating": false,
          "fallbackTo404": false,
          "default": false
        },
        {
          "uuid": "bbed157a-a492-4b50-9648-095c48dbf2c0",
          "body": "{}",
          "latency": 0,
          "statusCode": 200,
          "label": "commission-tab response",
          "headers": [
            {
              "key": "Content-Type",
              "value": "application/json"
            }
          ],
          "bodyType": "FILE",
          "filePath": "./activity/commission_tab.json",
          "databucketID": "",
          "sendFileAsBody": true,
          "rules": [
            {
              "target": "query",
              "modifier": "act",
              "value": "commssion",
              "invert": false,
              "operator": "equals"
            },
            {
              "target": "query",
              "modifier": "type",
              "value": "tab",
              "invert": false,
              "operator": "equals"
            }
          ],
          "rulesOperator": "AND",
          "disableTemplating": false,
          "fallbackTo404": false,
          "default": false
        },
        {
          "uuid": "af1643bd-64d8-44c5-aa53-246fd697ad3d",
          "body": "{}",
          "latency": 0,
          "statusCode": 200,
          "label": "commission-report response",
          "headers": [
            {
              "key": "Content-Type",
              "value": "application/json"
            }
          ],
          "bodyType": "FILE",
          "filePath": "./activity/commission_report.json",
          "databucketID": "",
          "sendFileAsBody": true,
          "rules": [
            {
              "target": "query",
              "modifier": "act",
              "value": "commission",
              "invert": false,
              "operator": "equals"
            },
            {
              "target": "query",
              "modifier": "type",
              "value": "report",
              "invert": false,
              "operator": "equals"
            }
          ],
          "rulesOperator": "AND",
          "disableTemplating": false,
          "fallbackTo404": false,
          "default": false
        }
      ],
      "enabled": true,
      "responseMode": null
    },
    {
      "uuid": "8d576b3c-a978-4102-b88a-f9c2d5388a4e",
      "type": "http",
      "documentation": "",
      "method": "get",
      "endpoint": "salary",
      "responses": [
        {
          "uuid": "fd5ef028-e077-4d68-b15b-0e1f518bcb8f",
          "body": "{}",
          "latency": 0,
          "statusCode": 200,
          "label": "page-open response",
          "headers": [
            {
              "key": "Content-Type",
              "value": "application/json"
            }
          ],
          "bodyType": "FILE",
          "filePath": "./salary/page_open.json",
          "databucketID": "",
          "sendFileAsBody": true,
          "rules": [
            {
              "target": "query",
              "modifier": "act",
              "value": "page",
              "invert": false,
              "operator": "equals"
            },
            {
              "target": "query",
              "modifier": "type",
              "value": "open",
              "invert": false,
              "operator": "equals"
            }
          ],
          "rulesOperator": "AND",
          "disableTemplating": false,
          "fallbackTo404": false,
          "default": true
        },
        {
          "uuid": "6e890823-22e4-416e-a27a-30ec8699fc15",
          "body": "{}",
          "latency": 0,
          "statusCode": 200,
          "label": "payroll-tab response",
          "headers": [
            {
              "key": "Content-Type",
              "value": "application/json"
            }
          ],
          "bodyType": "FILE",
          "filePath": "./salary/payroll_tab.json",
          "databucketID": "",
          "sendFileAsBody": true,
          "rules": [
            {
              "target": "query",
              "modifier": "act",
              "value": "payroll",
              "invert": false,
              "operator": "equals"
            },
            {
              "target": "query",
              "modifier": "type",
              "value": "tab",
              "invert": false,
              "operator": "equals"
            }
          ],
          "rulesOperator": "AND",
          "disableTemplating": false,
          "fallbackTo404": false,
          "default": false
        },
        {
          "uuid": "fcbed4e6-8a9f-4c8c-8086-a656b72013ed",
          "body": "{}",
          "latency": 0,
          "statusCode": 200,
          "label": "payroll-report response",
          "headers": [
            {
              "key": "Content-Type",
              "value": "application/json"
            }
          ],
          "bodyType": "FILE",
          "filePath": "./salary/payroll_report.json",
          "databucketID": "",
          "sendFileAsBody": true,
          "rules": [
            {
              "target": "query",
              "modifier": "act",
              "value": "payroll",
              "invert": false,
              "operator": "equals"
            },
            {
              "target": "query",
              "modifier": "type",
              "value": "report",
              "invert": false,
              "operator": "equals"
            }
          ],
          "rulesOperator": "AND",
          "disableTemplating": false,
          "fallbackTo404": false,
          "default": false
        },
        {
          "uuid": "80eaacf7-9430-43ce-aead-afddb59142c8",
          "body": "{}",
          "latency": 0,
          "statusCode": 200,
          "label": "ledger-tab response",
          "headers": [
            {
              "key": "Content-Type",
              "value": "application/json"
            }
          ],
          "bodyType": "FILE",
          "filePath": "./salary/ledger_tab.json",
          "databucketID": "",
          "sendFileAsBody": true,
          "rules": [
            {
              "target": "query",
              "modifier": "act",
              "value": "ledger",
              "invert": false,
              "operator": "equals"
            },
            {
              "target": "query",
              "modifier": "type",
              "value": "tab",
              "invert": false,
              "operator": "equals"
            }
          ],
          "rulesOperator": "AND",
          "disableTemplating": false,
          "fallbackTo404": false,
          "default": false
        },
        {
          "uuid": "de1a50a3-ca13-4a33-b59e-9683906dd89b",
          "body": "{}",
          "latency": 0,
          "statusCode": 200,
          "label": "ledger-report response",
          "headers": [
            {
              "key": "Content-Type",
              "value": "application/json"
            }
          ],
          "bodyType": "FILE",
          "filePath": "./salary/ledger_report.json",
          "databucketID": "",
          "sendFileAsBody": true,
          "rules": [
            {
              "target": "query",
              "modifier": "act",
              "value": "ledger",
              "invert": false,
              "operator": "equals"
            },
            {
              "target": "query",
              "modifier": "type",
              "value": "report",
              "invert": false,
              "operator": "equals"
            }
          ],
          "rulesOperator": "AND",
          "disableTemplating": false,
          "fallbackTo404": false,
          "default": false
        },
        {
          "uuid": "eb08d18f-eecf-4216-87e1-275d0010e882",
          "body": "{}",
          "latency": 0,
          "statusCode": 200,
          "label": "slip-tab response",
          "headers": [
            {
              "key": "Content-Type",
              "value": "application/json"
            }
          ],
          "bodyType": "FILE",
          "filePath": "./salary/slip_tab.json",
          "databucketID": "",
          "sendFileAsBody": true,
          "rules": [
            {
              "target": "query",
              "modifier": "act",
              "value": "slip",
              "invert": false,
              "operator": "equals"
            },
            {
              "target": "query",
              "modifier": "type",
              "value": "tab",
              "invert": false,
              "operator": "equals"
            }
          ],
          "rulesOperator": "AND",
          "disableTemplating": false,
          "fallbackTo404": false,
          "default": false
        },
        {
          "uuid": "06253ffa-e9e4-4f70-9a0d-4603fa3be38b",
          "body": "{}",
          "latency": 0,
          "statusCode": 200,
          "label": "slip-report response",
          "headers": [
            {
              "key": "Content-Type",
              "value": "application/json"
            }
          ],
          "bodyType": "FILE",
          "filePath": "./salary/slip_report.json",
          "databucketID": "",
          "sendFileAsBody": true,
          "rules": [
            {
              "target": "query",
              "modifier": "act",
              "value": "slip",
              "invert": false,
              "operator": "equals"
            },
            {
              "target": "query",
              "modifier": "type",
              "value": "report",
              "invert": false,
              "operator": "equals"
            }
          ],
          "rulesOperator": "AND",
          "disableTemplating": false,
          "fallbackTo404": false,
          "default": false
        }
      ],
      "enabled": true,
      "responseMode": null
    },
    {
      "uuid": "8cab63d3-87ce-4613-a746-0404d3149b49",
      "type": "http",
      "documentation": "",
      "method": "post",
      "endpoint": "activity",
      "responses": [
        {
          "uuid": "4a04849e-9563-4a27-8c15-4706b9a294ed",
          "body": "{}",
          "latency": 0,
          "statusCode": 200,
          "label": "page-open response",
          "headers": [
            {
              "key": "Content-Type",
              "value": "application/json"
            }
          ],
          "bodyType": "FILE",
          "filePath": "./activity/page_open.json",
          "databucketID": "",
          "sendFileAsBody": true,
          "rules": [
            {
              "target": "query",
              "modifier": "act",
              "value": "page",
              "invert": false,
              "operator": "equals"
            },
            {
              "target": "query",
              "modifier": "type",
              "value": "open",
              "invert": false,
              "operator": "equals"
            }
          ],
          "rulesOperator": "AND",
          "disableTemplating": false,
          "fallbackTo404": false,
          "default": true
        },
        {
          "uuid": "4266f050-8b1d-4f18-946d-56bdf963664d",
          "body": "{}",
          "latency": 0,
          "statusCode": 200,
          "label": "absents-tab response",
          "headers": [
            {
              "key": "Content-Type",
              "value": "application/json"
            }
          ],
          "bodyType": "FILE",
          "filePath": "./activity/absents_tab.json",
          "databucketID": "",
          "sendFileAsBody": true,
          "rules": [
            {
              "target": "query",
              "modifier": "act",
              "value": "absents",
              "invert": false,
              "operator": "equals"
            },
            {
              "target": "query",
              "modifier": "type",
              "value": "tab",
              "invert": false,
              "operator": "equals"
            }
          ],
          "rulesOperator": "AND",
          "disableTemplating": false,
          "fallbackTo404": false,
          "default": false
        },
        {
          "uuid": "8b0ecf95-d4ec-48e7-ba1f-6ecea2e8d961",
          "body": "{}",
          "latency": 0,
          "statusCode": 200,
          "label": "absents-report response",
          "headers": [
            {
              "key": "Content-Type",
              "value": "application/json"
            }
          ],
          "bodyType": "FILE",
          "filePath": "./activity/absents_report.json",
          "databucketID": "",
          "sendFileAsBody": true,
          "rules": [
            {
              "target": "query",
              "modifier": "act",
              "value": "absents",
              "invert": false,
              "operator": "equals"
            },
            {
              "target": "query",
              "modifier": "type",
              "value": "report",
              "invert": false,
              "operator": "equals"
            }
          ],
          "rulesOperator": "AND",
          "disableTemplating": false,
          "fallbackTo404": false,
          "default": false
        },
        {
          "uuid": "a5d9876f-521a-4eab-bb57-f3add5205689",
          "body": "{}",
          "latency": 0,
          "statusCode": 200,
          "label": "overtime-tab response",
          "headers": [
            {
              "key": "Content-Type",
              "value": "application/json"
            }
          ],
          "bodyType": "FILE",
          "filePath": "./activity/overtime_tab.json",
          "databucketID": "",
          "sendFileAsBody": true,
          "rules": [
            {
              "target": "query",
              "modifier": "act",
              "value": "overtime",
              "invert": false,
              "operator": "equals"
            },
            {
              "target": "query",
              "modifier": "type",
              "value": "tab",
              "invert": false,
              "operator": "equals"
            }
          ],
          "rulesOperator": "AND",
          "disableTemplating": false,
          "fallbackTo404": false,
          "default": false
        },
        {
          "uuid": "ec83c4be-fa5e-4ca1-a9c9-f7a1236a85fd",
          "body": "{}",
          "latency": 0,
          "statusCode": 200,
          "label": "overtime-report response",
          "headers": [
            {
              "key": "Content-Type",
              "value": "application/json"
            }
          ],
          "bodyType": "FILE",
          "filePath": "./activity/overtime_report.json",
          "databucketID": "",
          "sendFileAsBody": true,
          "rules": [
            {
              "target": "query",
              "modifier": "act",
              "value": "overtime",
              "invert": false,
              "operator": "equals"
            },
            {
              "target": "query",
              "modifier": "type",
              "value": "report",
              "invert": false,
              "operator": "equals"
            }
          ],
          "rulesOperator": "AND",
          "disableTemplating": false,
          "fallbackTo404": false,
          "default": false
        },
        {
          "uuid": "43c57425-3b05-4192-9f39-8bc95706e2cd",
          "body": "{}",
          "latency": 0,
          "statusCode": 200,
          "label": "expenses-tab response",
          "headers": [
            {
              "key": "Content-Type",
              "value": "application/json"
            }
          ],
          "bodyType": "FILE",
          "filePath": "./activity/expenses_tab.json",
          "databucketID": "",
          "sendFileAsBody": true,
          "rules": [
            {
              "target": "query",
              "modifier": "act",
              "value": "expenses",
              "invert": false,
              "operator": "equals"
            },
            {
              "target": "query",
              "modifier": "type",
              "value": "tab",
              "invert": false,
              "operator": "equals"
            }
          ],
          "rulesOperator": "AND",
          "disableTemplating": false,
          "fallbackTo404": false,
          "default": false
        },
        {
          "uuid": "1b22c4b2-8a8a-4e9d-9e9c-58e4e9083d48",
          "body": "{}",
          "latency": 0,
          "statusCode": 200,
          "label": "expenses-report response",
          "headers": [
            {
              "key": "Content-Type",
              "value": "application/json"
            }
          ],
          "bodyType": "FILE",
          "filePath": "./activity/expenses_report.json",
          "databucketID": "",
          "sendFileAsBody": true,
          "rules": [
            {
              "target": "query",
              "modifier": "act",
              "value": "expenses",
              "invert": false,
              "operator": "equals"
            },
            {
              "target": "query",
              "modifier": "type",
              "value": "report",
              "invert": false,
              "operator": "equals"
            }
          ],
          "rulesOperator": "AND",
          "disableTemplating": false,
          "fallbackTo404": false,
          "default": false
        },
        {
          "uuid": "298ec49a-3996-41ef-852a-feb69a4327e0",
          "body": "{}",
          "latency": 0,
          "statusCode": 200,
          "label": "shortage-tab response",
          "headers": [
            {
              "key": "Content-Type",
              "value": "application/json"
            }
          ],
          "bodyType": "FILE",
          "filePath": "./activity/shortage_tab.json",
          "databucketID": "",
          "sendFileAsBody": true,
          "rules": [
            {
              "target": "query",
              "modifier": "act",
              "value": "shortage",
              "invert": false,
              "operator": "equals"
            },
            {
              "target": "query",
              "modifier": "type",
              "value": "tab",
              "invert": false,
              "operator": "equals"
            }
          ],
          "rulesOperator": "AND",
          "disableTemplating": false,
          "fallbackTo404": false,
          "default": false
        },
        {
          "uuid": "3af8b8c5-0c2e-4c1f-b28f-f67a4c116dd2",
          "body": "{}",
          "latency": 0,
          "statusCode": 200,
          "label": "shortage-report response",
          "headers": [
            {
              "key": "Content-Type",
              "value": "application/json"
            }
          ],
          "bodyType": "FILE",
          "filePath": "./activity/shortage_report.json",
          "databucketID": "",
          "sendFileAsBody": true,
          "rules": [
            {
              "target": "query",
              "modifier": "act",
              "value": "shortage",
              "invert": false,
              "operator": "equals"
            },
            {
              "target": "query",
              "modifier": "type",
              "value": "report",
              "invert": false,
              "operator": "equals"
            }
          ],
          "rulesOperator": "AND",
          "disableTemplating": false,
          "fallbackTo404": false,
          "default": false
        },
        {
          "uuid": "8cc56eb8-8c00-46fb-9f68-f5976fbe0833",
          "body": "{}",
          "latency": 0,
          "statusCode": 200,
          "label": "commission-tab response",
          "headers": [
            {
              "key": "Content-Type",
              "value": "application/json"
            }
          ],
          "bodyType": "FILE",
          "filePath": "./activity/commission_tab.json",
          "databucketID": "",
          "sendFileAsBody": true,
          "rules": [
            {
              "target": "query",
              "modifier": "act",
              "value": "commssion",
              "invert": false,
              "operator": "equals"
            },
            {
              "target": "query",
              "modifier": "type",
              "value": "tab",
              "invert": false,
              "operator": "equals"
            }
          ],
          "rulesOperator": "AND",
          "disableTemplating": false,
          "fallbackTo404": false,
          "default": false
        },
        {
          "uuid": "ca7f88ae-bc73-4ce7-9cff-f7da966240b5",
          "body": "{}",
          "latency": 0,
          "statusCode": 200,
          "label": "commission-report response",
          "headers": [
            {
              "key": "Content-Type",
              "value": "application/json"
            }
          ],
          "bodyType": "FILE",
          "filePath": "./activity/commission_report.json",
          "databucketID": "",
          "sendFileAsBody": true,
          "rules": [
            {
              "target": "query",
              "modifier": "act",
              "value": "commission",
              "invert": false,
              "operator": "equals"
            },
            {
              "target": "query",
              "modifier": "type",
              "value": "report",
              "invert": false,
              "operator": "equals"
            }
          ],
          "rulesOperator": "AND",
          "disableTemplating": false,
          "fallbackTo404": false,
          "default": false
        }
      ],
      "enabled": true,
      "responseMode": null
    },
    {
      "uuid": "4cb59ef7-19e6-4a69-8ea0-12a93efbea04",
      "type": "http",
      "documentation": "",
      "method": "post",
      "endpoint": "salary",
      "responses": [
        {
          "uuid": "22b67c9a-8cc8-4173-a45d-d2161a3c188c",
          "body": "{}",
          "latency": 0,
          "statusCode": 200,
          "label": "page-open response",
          "headers": [
            {
              "key": "Content-Type",
              "value": "application/json"
            }
          ],
          "bodyType": "FILE",
          "filePath": "./salary/page_open.json",
          "databucketID": "",
          "sendFileAsBody": true,
          "rules": [
            {
              "target": "query",
              "modifier": "act",
              "value": "page",
              "invert": false,
              "operator": "equals"
            },
            {
              "target": "query",
              "modifier": "type",
              "value": "open",
              "invert": false,
              "operator": "equals"
            }
          ],
          "rulesOperator": "AND",
          "disableTemplating": false,
          "fallbackTo404": false,
          "default": true
        },
        {
          "uuid": "abfd5ad6-4f5c-4505-af9a-524a2ae98d1f",
          "body": "{}",
          "latency": 0,
          "statusCode": 200,
          "label": "payroll-tab response",
          "headers": [
            {
              "key": "Content-Type",
              "value": "application/json"
            }
          ],
          "bodyType": "FILE",
          "filePath": "./salary/payroll_tab.json",
          "databucketID": "",
          "sendFileAsBody": true,
          "rules": [
            {
              "target": "query",
              "modifier": "act",
              "value": "payroll",
              "invert": false,
              "operator": "equals"
            },
            {
              "target": "query",
              "modifier": "type",
              "value": "tab",
              "invert": false,
              "operator": "equals"
            }
          ],
          "rulesOperator": "AND",
          "disableTemplating": false,
          "fallbackTo404": false,
          "default": false
        },
        {
          "uuid": "ef25ca47-463f-4ec6-b693-f76a6fbc4139",
          "body": "{}",
          "latency": 0,
          "statusCode": 200,
          "label": "payroll-report response",
          "headers": [
            {
              "key": "Content-Type",
              "value": "application/json"
            }
          ],
          "bodyType": "FILE",
          "filePath": "./salary/payroll_report.json",
          "databucketID": "",
          "sendFileAsBody": true,
          "rules": [
            {
              "target": "query",
              "modifier": "act",
              "value": "payroll",
              "invert": false,
              "operator": "equals"
            },
            {
              "target": "query",
              "modifier": "type",
              "value": "report",
              "invert": false,
              "operator": "equals"
            }
          ],
          "rulesOperator": "AND",
          "disableTemplating": false,
          "fallbackTo404": false,
          "default": false
        },
        {
          "uuid": "b6e2a647-3ba1-423b-979f-67368b30024e",
          "body": "{}",
          "latency": 0,
          "statusCode": 200,
          "label": "ledger-tab response",
          "headers": [
            {
              "key": "Content-Type",
              "value": "application/json"
            }
          ],
          "bodyType": "FILE",
          "filePath": "./salary/ledger_tab.json",
          "databucketID": "",
          "sendFileAsBody": true,
          "rules": [
            {
              "target": "query",
              "modifier": "act",
              "value": "ledger",
              "invert": false,
              "operator": "equals"
            },
            {
              "target": "query",
              "modifier": "type",
              "value": "tab",
              "invert": false,
              "operator": "equals"
            }
          ],
          "rulesOperator": "AND",
          "disableTemplating": false,
          "fallbackTo404": false,
          "default": false
        },
        {
          "uuid": "8ae0679a-a0fc-4539-9c72-6ca556898526",
          "body": "{}",
          "latency": 0,
          "statusCode": 200,
          "label": "ledger-report response",
          "headers": [
            {
              "key": "Content-Type",
              "value": "application/json"
            }
          ],
          "bodyType": "FILE",
          "filePath": "./salary/ledger_report.json",
          "databucketID": "",
          "sendFileAsBody": true,
          "rules": [
            {
              "target": "query",
              "modifier": "act",
              "value": "ledger",
              "invert": false,
              "operator": "equals"
            },
            {
              "target": "query",
              "modifier": "type",
              "value": "report",
              "invert": false,
              "operator": "equals"
            }
          ],
          "rulesOperator": "AND",
          "disableTemplating": false,
          "fallbackTo404": false,
          "default": false
        },
        {
          "uuid": "48d56ad7-277b-46dd-b353-e5924fa0e363",
          "body": "{}",
          "latency": 0,
          "statusCode": 200,
          "label": "slip-tab response",
          "headers": [
            {
              "key": "Content-Type",
              "value": "application/json"
            }
          ],
          "bodyType": "FILE",
          "filePath": "./salary/slip_tab.json",
          "databucketID": "",
          "sendFileAsBody": true,
          "rules": [
            {
              "target": "query",
              "modifier": "act",
              "value": "slip",
              "invert": false,
              "operator": "equals"
            },
            {
              "target": "query",
              "modifier": "type",
              "value": "tab",
              "invert": false,
              "operator": "equals"
            }
          ],
          "rulesOperator": "AND",
          "disableTemplating": false,
          "fallbackTo404": false,
          "default": false
        },
        {
          "uuid": "533379d4-7e28-41ef-af07-45ea6ea79bce",
          "body": "{}",
          "latency": 0,
          "statusCode": 200,
          "label": "slip-report response",
          "headers": [
            {
              "key": "Content-Type",
              "value": "application/json"
            }
          ],
          "bodyType": "FILE",
          "filePath": "./salary/slip_report.json",
          "databucketID": "",
          "sendFileAsBody": true,
          "rules": [
            {
              "target": "query",
              "modifier": "act",
              "value": "slip",
              "invert": false,
              "operator": "equals"
            },
            {
              "target": "query",
              "modifier": "type",
              "value": "report",
              "invert": false,
              "operator": "equals"
            }
          ],
          "rulesOperator": "AND",
          "disableTemplating": false,
          "fallbackTo404": false,
          "default": false
        }
      ],
      "enabled": true,
      "responseMode": null
    }
  ],
  "rootChildren": [
    {
      "type": "folder",
      "uuid": "f096c391-569a-4824-8269-42c7f13e8039"
    },
    {
      "type": "folder",
      "uuid": "d6238eae-e512-4336-bb08-7867f5f57203"
    }
  ],
  "proxyMode": false,
  "proxyHost": "",
  "proxyRemovePrefix": false,
  "tlsOptions": {
    "enabled": false,
    "type": "CERT",
    "pfxPath": "",
    "certPath": "",
    "keyPath": "",
    "caPath": "",
    "passphrase": ""
  },
  "cors": true,
  "headers": [
    {
      "key": "Content-Type",
      "value": "application/json"
    },
    {
      "key": "Access-Control-Allow-Origin",
      "value": "*"
    },
    {
      "key": "Access-Control-Allow-Methods",
      "value": "GET,POST,PUT,PATCH,DELETE,HEAD,OPTIONS"
    },
    {
      "key": "Access-Control-Allow-Headers",
      "value": "Content-Type, Origin, Accept, Authorization, Content-Length, X-Requested-With"
    }
  ],
  "proxyReqHeaders": [
    {
      "key": "",
      "value": ""
    }
  ],
  "proxyResHeaders": [
    {
      "key": "",
      "value": ""
    }
  ],
  "data": []
}